iotools/__init__.py
iotools/buffer.hy
iotools/proto/__init__.py
iotools/proto/base.hy
iotools/proto/http.hy
iotools/proto/socks5.hy
iotools/proto/ssl.hy
iotools/proto/ws.hy
iotools/stream.hy
iotools/struct.hy
iotools/util.hy
iotools_hy-0.1.0.dist-info/METADATA
iotools_hy-0.1.0.dist-info/WHEEL
iotools_hy-0.1.0.dist-info/RECORD
